easycython/__init__.py
easycython/easycython.py
easycython-1.0.7.dist-info/DESCRIPTION.rst
easycython-1.0.7.dist-info/METADATA
easycython-1.0.7.dist-info/RECORD
easycython-1.0.7.dist-info/WHEEL
easycython-1.0.7.dist-info/entry_points.txt
easycython-1.0.7.dist-info/metadata.json
easycython-1.0.7.dist-info/top_level.txt
