Metadata-Version: 1.1
Name: easycython
Version: 1.0.7
Summary: Compile .pyx to (.pyd|.so) very easily.
Home-page: https://github.com/cjrh/easycython
Author: Caleb Hattingh
Author-email: caleb.hattingh@gmail.com
License: MIT
Keywords: cython
Platform: UNKNOWN
Classifier: Development Status :: 4 - Beta
Classifier: Environment :: Console
Classifier: Intended Audience :: Developers
Classifier: Intended Audience :: Science/Research
Classifier: Topic :: Software Development :: Build Tools
Classifier: Programming Language :: Cython
Classifier: License :: OSI Approved :: MIT License
Classifier: Programming Language :: Python :: 2
Classifier: Programming Language :: Python :: 2.7
Classifier: Programming Language :: Python :: 3
Classifier: Programming Language :: Python :: 3.4
Classifier: Topic :: Software Development :: Build Tools
